MolLayers/__init__.py
MolLayers/engine.py
MolLayers/modules/__init__.py
MolLayers/modules/atom_selection_config.py
MolLayers/modules/channels.py
MolLayers/modules/input_file_parser.py
MolLayers-0.1.0.dist-info/LICENSE
MolLayers-0.1.0.dist-info/METADATA
MolLayers-0.1.0.dist-info/WHEEL
MolLayers-0.1.0.dist-info/top_level.txt
MolLayers-0.1.0.dist-info/RECORD
