Metadata-Version: 2.1
Name: MolLayers
Version: 0.1.0
Summary: Implementation of Layers algorithm adapting Biopython file parsers
Home-page: https://www.nbrkarampudi.org
Author: nbrkarampudi
Author-email: nagabhushan.k@srmap.edu.in
License: GNU GPL3
Classifier: Environment :: Console
Classifier: Intended Audience :: Developers
Classifier: Operating System :: OS Independent
Classifier: Programming Language :: Python :: 3
License-File: LICENSE
Requires-Dist: biopython (>=1.7)
Requires-Dist: mmtf-python (>=1.1)
